{
  "project_info": {
    "project_number": "436882447188",
    "project_id": "flashfuel-2c9c2",
    "storage_bucket": "flashfuel-2c9c2.firebasestorage.app"
  },
  "client": [
    {
      "client_info": {
        "mobilesdk_app_id": "1:436882447188:android:23c7685b3a033ba2ad06c1",
        "android_client_info": {
          "package_name": "com.example.demo_flash_fuel"
        }
      },
      "oauth_client": [],
      "api_key": [
        {
          "current_key": "AIzaSyA2PeWY9eggnj6PedWT5Y3efpXYe9FjsKs"
        }
      ],
      "services": {
        "appinvite_service": {
          "other_platform_oauth_client": []
        }
      }
    }
  ],
  "configuration_version": "1"
}